us_routing/__init__.py
us_routing/_download.py
us_routing/common.py
us_routing/domain.py
us_routing/router.py
us_routing-0.1.0.dist-info/METADATA
us_routing-0.1.0.dist-info/WHEEL
us_routing-0.1.0.dist-info/RECORD
