Metadata-Version: 2.1
Name: us-routing
Version: 0.1.0
Summary: US Routing is a Python library for fast local routing in the United States. Useful when approximations are acceptable.
Author: ivanbelenky
Author-email: ivandietert@gmail.com
Requires-Python: >=3.11,<3.12
Classifier: Programming Language :: Python :: 3
Classifier: Programming Language :: Python :: 3.11
Requires-Dist: geopandas (>=1.0.1,<2.0.0)
Requires-Dist: networkx (>=3.3,<4.0)
Requires-Dist: numpy (>=2.1.0,<3.0.0)
Requires-Dist: pandas (>=2.2.2,<3.0.0)
Requires-Dist: pydantic (>=2.8.2,<3.0.0)
Requires-Dist: python-levenshtein (>=0.25.1,<0.26.0)
Requires-Dist: requests (>=2.32.3,<3.0.0)
Requires-Dist: rtree (>=1.3.0,<2.0.0)
Requires-Dist: sqlalchemy-mate (==2.0.0)
Requires-Dist: tqdm (>=4.66.5,<5.0.0)
Requires-Dist: uszipcode (>=1.0.1,<2.0.0)
